{"id": 7661, "amount": 30.22, "paid": true}
{"id": 7662, "amount": 485.11, "paid": true}
{"id": 7663, "amount": 36.29, "paid": true}
{"id": 7664, "amount": 289.95, "paid": true}
{"id": 7665, "amount": 2.26, "paid": false}
{"id": 7666, "amount": 21.94, "paid": false}
{"id": 7667, "amount": 496.84, "paid": false}
{"id": 7668, "amount": 388.88, "paid": true}
{"id": 7669, "amount": 369.35, "paid": false}
{"id": 7670, "amount": 498.21, "paid": false}
{"id": 7671, "amount": 386.82, "paid": false}
{"id": 7672, "amount": 412.4, "paid": false}
{"id": 7673, "amount": 256.61, "paid": true}
{"id": 7674, "amount": 136.13, "paid": false}
{"id": 7675, "amount": 35.52, "paid": false}
{"id": 7676, "amount": 234.0, "paid": false}
{"id": 7677, "amount": 203.17, "paid": true}
{"id": 7678, "amount": 251.1, "paid": false}
{"id": 7679, "amount": 39.43, "paid": true}
{"id": 7680, "amount": 402.88, "paid": true}
