{"id": 7581, "amount": 97.71, "paid": true}
{"id": 7582, "amount": 25.33, "paid": true}
{"id": 7583, "amount": 361.92, "paid": true}
{"id": 7584, "amount": 19.84, "paid": true}
{"id": 7585, "amount": 118.7, "paid": false}
{"id": 7586, "amount": 138.48, "paid": false}
{"id": 7587, "amount": 426.11, "paid": true}
{"id": 7588, "amount": 438.92, "paid": true}
{"id": 7589, "amount": 250.08, "paid": false}
{"id": 7590, "amount": 268.4, "paid": false}
{"id": 7591, "amount": 428.7, "paid": false}
{"id": 7592, "amount": 36.08, "paid": false}
{"id": 7593, "amount": 206.56, "paid": true}
{"id": 7594, "amount": 441.96, "paid": true}
{"id": 7595, "amount": 191.46, "paid": true}
{"id": 7596, "amount": 232.51, "paid": true}
{"id": 7597, "amount": 181.98, "paid": true}
{"id": 7598, "amount": 217.61, "paid": false}
{"id": 7599, "amount": 407.53, "paid": true}
{"id": 7600, "amount": 73.63, "paid": false}
