{"id": 1081, "amount": 413.1}
{"id": 1082, "amount": 480.97}
{"id": 1083, "amount": 362.41}
{"id": 1084, "amount": 66.57}
{"id": 1085, "amount": 440.18}
{"id": 1086, "amount": 159.06}
{"id": 1087, "amount": 255.98}
{"id": 1088, "amount": 6.64}
{"id": 1089, "amount": 367.3}
{"id": 1090, "amount": 270.15}
{"id": 1091, "amount": 296.52}
{"id": 1092, "amount": 380.45}
{"id": 1093, "amount": 80.08}
{"id": 1094, "amount": 112.87}
{"id": 1095, "amount": 109.19}
{"id": 1096, "amount": 144.86}
{"id": 1097, "amount": 52.04}
{"id": 1098, "amount": 173.56}
{"id": 1099, "amount": 132.13}
{"id": 1100, "amount": 121.17}
